{
  "citation": "",
  "description": "",
  "features": {
    "instance": {
      "dtype": "string",
      "_type": "Value"
    },
    "problem": {
      "dtype": "string",
      "_type": "Value"
    },
    "timestamp": {
      "dtype": "int64",
      "_type": "Value"
    },
    "correct_program_lines": {
      "feature": {
        "dtype": "string",
        "_type": "Value"
      },
      "_type": "Sequence"
    },
    "correct_program": {
      "dtype": "string",
      "_type": "Value"
    },
    "reference_program_lines": {
      "feature": {
        "dtype": "string",
        "_type": "Value"
      },
      "_type": "Sequence"
    },
    "reference_program": {
      "dtype": "string",
      "_type": "Value"
    },
    "incorrect_program_lines": {
      "feature": {
        "dtype": "string",
        "_type": "Value"
      },
      "_type": "Sequence"
    },
    "incorrect_program": {
      "dtype": "string",
      "_type": "Value"
    },
    "correction": {
      "feature": {
        "dtype": "string",
        "_type": "Value"
      },
      "_type": "Sequence"
    },
    "n_mutations": {
      "dtype": "int64",
      "_type": "Value"
    },
    "missing_lines": {
      "dtype": "bool",
      "_type": "Value"
    },
    "n_mising_lines": {
      "dtype": "int64",
      "_type": "Value"
    },
    "fl": {
      "feature": {
        "dtype": "int64",
        "_type": "Value"
      },
      "_type": "Sequence"
    },
    "line_scores": {
      "feature": {
        "dtype": "float64",
        "_type": "Value"
      },
      "_type": "Sequence"
    },
    "__index_level_0__": {
      "dtype": "int64",
      "_type": "Value"
    }
  },
  "homepage": "",
  "license": ""
}